jiwer/__init__.py
jiwer/alignment.py
jiwer/cli.py
jiwer/measures.py
jiwer/process.py
jiwer/transformations.py
jiwer/transforms.py
jiwer-3.0.0.dist-info/LICENSE
jiwer-3.0.0.dist-info/METADATA
jiwer-3.0.0.dist-info/WHEEL
jiwer-3.0.0.dist-info/entry_points.txt
jiwer-3.0.0.dist-info/RECORD
