Metadata-Version: 2.1
Name: jiwer
Version: 3.0.0
Summary: Evaluate your speech-to-text system with similarity measures such as word error rate (WER)
Home-page: https://github.com/jitsi/jiwer
License: Apache-2.0
Author: Nik Vaessen
Author-email: nikvaes@gmail.com
Requires-Python: >=3.7,<4.0
Classifier: License :: OSI Approved :: Apache Software License
Classifier: Programming Language :: Python :: 3
Classifier: Programming Language :: Python :: 3.7
Classifier: Programming Language :: Python :: 3.8
Classifier: Programming Language :: Python :: 3.9
Classifier: Programming Language :: Python :: 3.10
Classifier: Programming Language :: Python :: 3.11
Requires-Dist: click (>=8.1.3,<9.0.0)
Requires-Dist: rapidfuzz (==2.13.7)
Project-URL: Repository, https://github.com/jitsi/jiwer
